odoo/addons/l10n_it_withholding_tax_causali/README.rst
odoo/addons/l10n_it_withholding_tax_causali/__init__.py
odoo/addons/l10n_it_withholding_tax_causali/__manifest__.py
odoo/addons/l10n_it_withholding_tax_causali/i18n/it.po
odoo/addons/l10n_it_withholding_tax_causali/i18n/l10n_it_withholding_tax_causali.pot
odoo/addons/l10n_it_withholding_tax_causali/models/__init__.py
odoo/addons/l10n_it_withholding_tax_causali/models/withholding_tax.py
odoo/addons/l10n_it_withholding_tax_causali/readme/DESCRIPTION.rst
odoo/addons/l10n_it_withholding_tax_causali/static/description/icon.png
odoo/addons/l10n_it_withholding_tax_causali/static/description/index.html
odoo/addons/l10n_it_withholding_tax_causali/views/withholding_tax.xml
odoo11_addon_l10n_it_withholding_tax_causali-11.0.1.0.0.99.dev4.dist-info/METADATA
odoo11_addon_l10n_it_withholding_tax_causali-11.0.1.0.0.99.dev4.dist-info/WHEEL
odoo11_addon_l10n_it_withholding_tax_causali-11.0.1.0.0.99.dev4.dist-info/top_level.txt
odoo11_addon_l10n_it_withholding_tax_causali-11.0.1.0.0.99.dev4.dist-info/RECORD
